nn_calc.py
nn_calc-0.1.2.dist-info/licenses/LICENSE
nn_calc-0.1.2.dist-info/METADATA
nn_calc-0.1.2.dist-info/WHEEL
nn_calc-0.1.2.dist-info/entry_points.txt
nn_calc-0.1.2.dist-info/top_level.txt
nn_calc-0.1.2.dist-info/RECORD
